{"errors":[],"warnings":[],"namedChunkGroups":{"polyfill":{"chunks":[2,10],"assets":["webpack-runtime-1fc3c9b740fe94d4148d.js","webpack-runtime-1fc3c9b740fe94d4148d.js.map","polyfill-2966d4d8fea208fd6f8f.js","polyfill-2966d4d8fea208fd6f8f.js.map"],"children":{},"childAssets":{}},"app":{"chunks":[2,9,3],"assets":["webpack-runtime-1fc3c9b740fe94d4148d.js","webpack-runtime-1fc3c9b740fe94d4148d.js.map","framework-de237a875aa45b276a9d.js","framework-de237a875aa45b276a9d.js.map","app-2722efca7d95a25e4adb.js","app-2722efca7d95a25e4adb.js.map"],"children":{},"childAssets":{}},"component---src-pages-404-js":{"chunks":[1,0,4],"assets":["styles.9b4500260357dc3df222.css","styles-e9d24b1846c7d6eb9685.js","styles-e9d24b1846c7d6eb9685.js.map","commons-b170c8909f2bde4fd05f.js","commons-b170c8909f2bde4fd05f.js.map","component---src-pages-404-js-9c04155390b493ad90ef.js","component---src-pages-404-js-9c04155390b493ad90ef.js.map"],"children":{},"childAssets":{}},"component---src-pages-index-js":{"chunks":[1,0,5],"assets":["styles.9b4500260357dc3df222.css","styles-e9d24b1846c7d6eb9685.js","styles-e9d24b1846c7d6eb9685.js.map","commons-b170c8909f2bde4fd05f.js","commons-b170c8909f2bde4fd05f.js.map","component---src-pages-index-js-598c0127065a5298a230.js","component---src-pages-index-js-598c0127065a5298a230.js.map"],"children":{},"childAssets":{}},"component---src-pages-page-2-js":{"chunks":[1,0,6],"assets":["styles.9b4500260357dc3df222.css","styles-e9d24b1846c7d6eb9685.js","styles-e9d24b1846c7d6eb9685.js.map","commons-b170c8909f2bde4fd05f.js","commons-b170c8909f2bde4fd05f.js.map","component---src-pages-page-2-js-6f9304e8e0b72f58449a.js","component---src-pages-page-2-js-6f9304e8e0b72f58449a.js.map"],"children":{},"childAssets":{}},"component---src-pages-page-3-js":{"chunks":[1,0,7],"assets":["styles.9b4500260357dc3df222.css","styles-e9d24b1846c7d6eb9685.js","styles-e9d24b1846c7d6eb9685.js.map","commons-b170c8909f2bde4fd05f.js","commons-b170c8909f2bde4fd05f.js.map","component---src-pages-page-3-js-a5ab23bd2d95c10aebd4.js","component---src-pages-page-3-js-a5ab23bd2d95c10aebd4.js.map"],"children":{},"childAssets":{}},"component---src-pages-using-typescript-tsx":{"chunks":[1,0,8],"assets":["styles.9b4500260357dc3df222.css","styles-e9d24b1846c7d6eb9685.js","styles-e9d24b1846c7d6eb9685.js.map","commons-b170c8909f2bde4fd05f.js","commons-b170c8909f2bde4fd05f.js.map","component---src-pages-using-typescript-tsx-e8bf57fe439c2c60ca32.js","component---src-pages-using-typescript-tsx-e8bf57fe439c2c60ca32.js.map"],"children":{},"childAssets":{}}},"assetsByChunkName":{"polyfill":["webpack-runtime-1fc3c9b740fe94d4148d.js","polyfill-2966d4d8fea208fd6f8f.js"],"app":["webpack-runtime-1fc3c9b740fe94d4148d.js","framework-de237a875aa45b276a9d.js","app-2722efca7d95a25e4adb.js"],"component---src-pages-404-js":["styles.9b4500260357dc3df222.css","styles-e9d24b1846c7d6eb9685.js","commons-b170c8909f2bde4fd05f.js","component---src-pages-404-js-9c04155390b493ad90ef.js"],"component---src-pages-index-js":["styles.9b4500260357dc3df222.css","styles-e9d24b1846c7d6eb9685.js","commons-b170c8909f2bde4fd05f.js","component---src-pages-index-js-598c0127065a5298a230.js"],"component---src-pages-page-2-js":["styles.9b4500260357dc3df222.css","styles-e9d24b1846c7d6eb9685.js","commons-b170c8909f2bde4fd05f.js","component---src-pages-page-2-js-6f9304e8e0b72f58449a.js"],"component---src-pages-page-3-js":["styles.9b4500260357dc3df222.css","styles-e9d24b1846c7d6eb9685.js","commons-b170c8909f2bde4fd05f.js","component---src-pages-page-3-js-a5ab23bd2d95c10aebd4.js"],"component---src-pages-using-typescript-tsx":["styles.9b4500260357dc3df222.css","styles-e9d24b1846c7d6eb9685.js","commons-b170c8909f2bde4fd05f.js","component---src-pages-using-typescript-tsx-e8bf57fe439c2c60ca32.js"]}}